{
  "certifications": [
    {
      "title": "C2i",
      "link": "https://c2i.enseignementsup-recherche.gouv.fr/employeur/faq-employeur",
      "date": "2014-01-01",
      "description": ""
    },
    {
      "title": "Opquast",
      "date": "2017-07-04",
      "link": "https://certificates.opquast.com/certificate/JYLOBQ/",
      "description": "Certification passée lors de ma licence professionnelle DAWIN. Score de 900 points."
    },
    {
      "title": "TOEIC",
      "date": "2018-02-01",
      "link": "https://www.ets.org/fr/toeic",
      "description": "J'ai passé et obtenu mon TOEIC à 3 reprises au cours de mes études, du fait qu'il était obligatoire d'avoir un TOEIC en cours de validité afin de valider mon diplôme bac+5. Score obtenu au dernier passage : 855 / 1000."
    },
    {
      "title": "AWS Certified Solutions Architect – Associate",
      "date": "2021-07-08",
      "link": "https://www.credly.com/badges/8cbf3caf-31e1-49d1-af48-aa6750286e0a/public_url",
      "description": ""
    }
  ]
}
